django_archive/__init__.py
django_archive/archivers/__init__.py
django_archive/archivers/tarball.py
django_archive/archivers/zipfile.py
django_archive/management/__init__.py
django_archive/management/commands/__init__.py
django_archive/management/commands/archive.py
django_archive/util/__init__.py
django_archive/util/file.py
django_archive-0.2.0.dist-info/LICENSE.txt
django_archive-0.2.0.dist-info/METADATA
django_archive-0.2.0.dist-info/WHEEL
django_archive-0.2.0.dist-info/top_level.txt
django_archive-0.2.0.dist-info/RECORD
